{
  "placeholderImages": [
    {
      "id": "hero-market",
      "category": "hero",
      "description": "A vibrant and colorful Indian farmer's market stall filled with fresh vegetables.",
      "imageUrl": "https://images.unsplash.com/photo-1598154030351-a83161f3f652?crop=entropy&cs=tinysrgb&fit=max&fm=jpg&ixid=M3w3NDE5ODJ8MHwxfHNlYXJjaHw4fHxpbmRpYW4lMjB2ZWdldGFibGUlMjBtYXJrZXR8ZW58MHx8fHwxNzYxMDUzMjM3fDA&ixlib=rb-4.1.0&q=80&w=1080",
      "imageHint": "indian vegetable market"
    },
    {
      "id": "tomatoes",
      "category": "product",
      "productType": "vegetables",
      "description": "Fresh red tomatoes on a vine",
      "imageUrl": "https://images.unsplash.com/photo-1591171551239-80a5eddd627a?crop=entropy&cs=tinysrgb&fit=max&fm=jpg&ixid=M3w3NDE5ODJ8MHwxfHNlYXJjaHw3fHxmcmVzaCUyMHRvbWF0b2VzfGVufDB8fHx8MTc2MDg3ODI5M3ww&ixlib=rb-4.1.0&q=80&w=1080",
      "imageHint": "fresh tomatoes",
      "name": "देसी टमाटर (Desi Tomato)",
      "price": "40",
      "farmer": "Pawar Farms"
    },
    {
      "id": "potatoes",
      "category": "product",
      "productType": "vegetables",
      "description": "Earthy potatoes freshly harvested",
      "imageUrl": "https://images.unsplash.com/photo-1571771894821-35f15933a274?crop=entropy&cs=tinysrgb&fit=max&fm=jpg&ixid=M3w3NDE5ODJ8MHwxfHNlYXJjaHwxfHxpbmRpYW4lMjBwb3RhdG9lc3xlbnwwfHx8fDE3NjA5Njc1MDh8MA&ixlib=rb-4.1.0&q=80&w=1080",
      "imageHint": "fresh potatoes",
      "name": "बटाटा (Potato)",
      "price": "30",
      "farmer": "Shinde Organics"
    },
    {
      "id": "basmati-rice",
      "category": "product",
      "productType": "grains",
      "description": "Long-grain Basmati rice in a burlap sack",
      "imageUrl": "https://images.unsplash.com/photo-1586201375765-c124a9539d5e?crop=entropy&cs=tinysrgb&fit=max&fm=jpg&ixid=M3w3NDE5ODJ8MHwxfHNlYXJjaHwxfHxiYXNtYXRpJTIwcmljZXxlbnwwfHx8fDE3NjA5Njc1NjZ8MA&ixlib=rb-4.1.0&q=80&w=1080",
      "imageHint": "basmati rice",
      "name": "बासमती चावल (Basmati Rice)",
      "price": "120",
      "farmer": "Golden Fields"
    },
    {
      "id": "mangoes",
      "category": "product",
      "productType": "fruits",
      "description": "Ripe Alphonso mangoes in a basket",
      "imageUrl": "https://images.unsplash.com/photo-1622005051834-58a4369f390d?crop=entropy&cs=tinysrgb&fit=max&fm=jpg&ixid=M3w3NDE5ODJ8MHwxfHNlYXJjaHwxfHxhbHBob25zbyUyMG1hbmdvZXN8ZW58MHx8fHwxNzYwOTY3NjIwfDA&ixlib=rb-4.1.0&q=80&w=1080",
      "imageHint": "alphonso mangoes",
      "name": "आम (Alphonso Mango)",
      "price": "800",
      "farmer": "Ratnagiri Farms"
    },
    {
      "id": "spinach",
      "category": "product",
      "productType": "vegetables",
      "description": "Fresh green spinach leaves",
      "imageUrl": "https://images.unsplash.com/photo-1576045057995-568f588f21fb?crop=entropy&cs=tinysrgb&fit=max&fm=jpg&ixid=M3w3NDE5ODJ8MHwxfHNlYXJjaHwxfHxmcmVzaCUyMHNwaW5hY2h8ZW58MHx8fHwxNzYwODUxODk4fDA&ixlib=rb-4.1.0&q=80&w=1080",
      "imageHint": "fresh spinach",
      "name": "पालक (Spinach)",
      "price": "20",
      "farmer": "Pawar Farms"
    },
    {
      "id": "onions",
      "category": "product",
      "productType": "vegetables",
      "description": "Fresh red onions",
      "imageUrl": "https://images.unsplash.com/photo-1588114480643-d3a3b022dc7e?crop=entropy&cs=tinysrgb&fit=max&fm=jpg&ixid=M3w3NDE5ODJ8MHwxfHNlYXJjaHwxfHxyZWQlMjBvbmlvbnN8ZW58MHx8fHwxNzYwOTY3NzQ4fDA&ixlib=rb-4.1.0&q=80&w=1080",
      "imageHint": "red onions",
      "name": "प्याज (Onion)",
      "price": "50",
      "farmer": "Shinde Organics"
    },
    {
      "id": "turmeric",
      "category": "product",
      "productType": "spices",
      "description": "Turmeric powder and roots",
      "imageUrl": "https://images.unsplash.com/photo-1596035242942-ecb8a7c1b5e2?crop=entropy&cs=tinysrgb&fit=max&fm=jpg&ixid=M3w3NDE5ODJ8MHwxfHNlYXJjaHwxfHx0dXJtZXJpYyUyMHJvb3RzfGVufDB8fHx8MTc2MTA1Mzk5OXww&ixlib=rb-4.1.0&q=80&w=1080",
      "imageHint": "turmeric roots",
      "name": "हल्दी (Turmeric)",
      "price": "250",
      "farmer": "Golden Fields"
    },
    {
      "id": "pomegranate",
      "category": "product",
      "productType": "fruits",
      "description": "A ripe pomegranate",
      "imageUrl": "https://images.unsplash.com/photo-1631771967237-f1c422c15989?crop=entropy&cs=tinysrgb&fit=max&fm=jpg&ixid=M3w3NDE5ODJ8MHwxfHNlYXJjaHwxfHxwb21lZ3JhbmF0ZSUyMGZydWl0fGVufDB8fHx8MTc2MTA1NDA0Nnww&ixlib=rb-4.1.0&q=80&w=1080",
      "imageHint": "pomegranate fruit",
      "name": "अनार (Pomegranate)",
      "price": "150",
      "farmer": "Ratnagiri Farms"
    },
    {
      "id": "lentils",
      "category": "product",
      "productType": "pulses",
      "description": "Bowl of red lentils",
      "imageUrl": "https://images.unsplash.com/photo-1583349642643-a6294a8f9b97?crop=entropy&cs=tinysrgb&fit=max&fm=jpg&ixid=M3w3NDE5ODJ8MHwxfHNlYXJjaHwxfHxyZWQlMjBsZW50aWxzfGVufDB8fHx8MTc2MTI5NjI2OXww&ixlib=rb-4.1.0&q=80&w=1080",
      "imageHint": "red lentils",
      "name": "मसूर दाल (Masoor Dal)",
      "price": "90",
      "farmer": "Golden Fields"
    },
    {
      "id": "marigold",
      "category": "product",
      "productType": "flowers",
      "description": "Bright orange marigold flowers",
      "imageUrl": "https://images.unsplash.com/photo-1594290358414-81413a7384a5?crop=entropy&cs=tinysrgb&fit=max&fm=jpg&ixid=M3w3NDE5ODJ8MHwxfHNlYXJjaHwxfHxtYXJpZ29sZCUyMGZsb3dlcnN8ZW58MHx8fHwxNzYxMjk2MzE3fDA&ixlib=rb-4.1.0&q=80&w=1080",
      "imageHint": "marigold flowers",
      "name": "गेंदा (Marigold)",
      "price": "50",
      "farmer": "Pawar Farms"
    },
    {
      "id": "tutorial1",
      "category": "learning",
      "description": "A farmer inspecting crops in a field, representing a tutorial on crop management.",
      "imageUrl": "https://images.unsplash.com/photo-1499529112087-3cb3b73cec95?crop=entropy&cs=tinysrgb&fit=max&fm=jpg&ixid=M3w3NDE5ODJ8MHwxfHNlYXJjaHwxfHxmYXJtZXIlMjBpbnNwZWN0aW5nJTIwY3JvcHN8ZW58MHx8fHwxNzYxMDU0MTIyfDA&ixlib=rb-4.1.0&q=80&w=1080",
      "imageHint": "farmer inspecting crops"
    },
    {
      "id": "webinar1",
      "category": "learning",
      "description": "A person giving a presentation, representing a webinar on modern farming techniques.",
      "imageUrl": "https://images.unsplash.com/photo-1556761175-b413da4b248b?crop=entropy&cs=tinysrgb&fit=max&fm=jpg&ixid=M3w3NDE5ODJ8MHwxfHNlYXJjaHwxfHxidXNpbmVzcyUyMHdlYmluYXJ8ZW58MHx8fHwxNzYxMDU0MTg3fDA&ixlib=rb-4.1.0&q=80&w=1080",
      "imageHint": "business webinar"
    },
    {
      "id": "resource1",
      "category": "learning",
      "description": "An open book with illustrations of plants, representing a downloadable guide.",
      "imageUrl": "https://images.unsplash.com/photo-1495446815901-a7297e633e8d?crop=entropy&cs=tinysrgb&fit=max&fm=jpg&ixid=M3w3NDE5ODJ8MHwxfHNlYXJjaHwxfHxyZWFkaW5nJTIwYm9va3xlbnwwfHx8fDE3NjEwNTQyNDd8MA&ixlib=rb-4.1.0&q=80&w=1080",
      "imageHint": "reading book"
    },
    {
      "id": "tutorial2",
      "category": "learning",
      "description": "Close up of hands holding rich soil.",
      "imageUrl": "https://images.unsplash.com/photo-1594245667954-4161f36599b4?crop=entropy&cs=tinysrgb&fit=max&fm=jpg&ixid=M3w3NDE5ODJ8MHwxfHNlYXJjaHwxfHxzb2lsJTIwaGVhbHRofGVufDB8fHx8MTc2MDg4MDE3OHww&ixlib=rb-4.1.0&q=80&w=1080",
      "imageHint": "soil health"
    },
    {
      "id": "schemes-hero",
      "category": "hero",
      "description": "An Indian farmer smiling in a field.",
      "imageUrl": "https://images.unsplash.com/photo-1617192213511-2c9a1a63de40?crop=entropy&cs=tinysrgb&fit=max&fm=jpg&ixid=M3w3NDE5ODJ8MHwxfHNlYXJjaHwxfHxpbmRpYW4lMjBmYXJtZXJ8ZW58MHx8fHwxNzYxMDU0MzcyfDA&ixlib=rb-4.1.0&q=80&w=1080",
      "imageHint": "indian farmer"
    },
    {
      "id": "bulk-hero",
      "category": "hero",
      "description": "A crate of fresh vegetables ready for bulk delivery.",
      "imageUrl": "https://images.unsplash.com/photo-1540914124281-3425879413d5?crop=entropy&cs=tinysrgb&fit=max&fm=jpg&ixid=M3w3NDE5ODJ8MHwxfHNlYXJjaHwxfHxmcmVzaCUyMHZlZ2V0YWJsZXMlMjBjcmF0ZXxlbnwwfHx8fDE3NjEwNTAyNjR8MA&ixlib=rb-4.1.0&q=80&w=1080",
      "imageHint": "vegetable crate"
    },
    {
      "id": "subscription-hero",
      "category": "hero",
      "description": "A person holding a subscription box full of fresh produce.",
      "imageUrl": "https://images.unsplash.com/photo-1601614389617-4a51996773a4?crop=entropy&cs=tinysrgb&fit=max&fm=jpg&ixid=M3w3NDE5ODJ8MHwxfHNlYXJjaHwxfHxwcm9kdWNlJTIwc3Vic2NyaXB0aW9uJTIwYm94fGVufDB8fHx8MTc2MTA1NDQ4N3ww&ixlib=rb-4.1.0&q=80&w=1080",
      "imageHint": "produce subscription box"
    },
    {
      "id": "tutorial3",
      "category": "learning",
      "description": "Farmer using a laptop in a field",
      "imageUrl": "https://images.unsplash.com/photo-1560493676-04071c5f467b?crop=entropy&cs=tinysrgb&fit=max&fm=jpg&ixid=M3w3NDE5ODJ8MHwxfHNlYXJjaHwxfHxmYXJtZXIlMjB3aXRoJTIwbGFwdG9wfGVufDB8fHx8fDE3NjEwNTQ1Mzh8MA&ixlib=rb-4.1.0&q=80&w=1080",
      "imageHint": "farmer with laptop"
    }
  ]
}